joker_broker-0.0.12-py3.5-nspkg.pth
joker/broker/__init__.py
joker/broker/access.py
joker/broker/check.py
joker/broker/logging.py
joker/broker/model.py
joker/broker/security.py
joker/broker/userdefault.py
joker/broker/interfaces/__init__.py
joker/broker/interfaces/redis.py
joker/broker/interfaces/sequel.py
joker/broker/interfaces/static.py
joker_broker-0.0.12.dist-info/DESCRIPTION.rst
joker_broker-0.0.12.dist-info/METADATA
joker_broker-0.0.12.dist-info/RECORD
joker_broker-0.0.12.dist-info/WHEEL
joker_broker-0.0.12.dist-info/metadata.json
joker_broker-0.0.12.dist-info/namespace_packages.txt
joker_broker-0.0.12.dist-info/top_level.txt
